[{"teamSlug":"Aberdeen","schoolAffiliation":"MHSAA","schoolTown":"Aberdeen","schoolCounty":"Monroe","schoolDistrict":"Aberdeen School District"},{"teamSlug":"Adamscountychristian","schoolAffiliation":"MAIS","schoolTown":"Natchez","schoolCounty":"Adams"},{"teamSlug":"Alcorncentral","schoolAffiliation":"MHSAA","schoolTown":"Glen","schoolCounty":"Alcorn","schoolDistrict":"Alcorn County School District"},{"teamSlug":"Amite","schoolAffiliation":"MAIS","schoolTown":"Liberty","schoolCounty":"Amite"},{"teamSlug":"Amitecounty","schoolAffiliation":"MHSAA","schoolTown":"Liberty","schoolCounty":"Amite","schoolDistrict":"Amite County School District"},{"teamSlug":"Amory","schoolAffiliation":"MHSAA","schoolTown":"Amory","schoolCounty":"Monroe","schoolDistrict":"Amory School District"},{"teamSlug":"Ashland","schoolAffiliation":"MHSAA","schoolTown":"Ashland","schoolCounty":"Benton","schoolDistrict":"Benton County School District"},{"teamSlug":"Baldwyn","schoolAffiliation":"MHSAA","schoolTown":"Baldwyn","schoolCounty":"Prentiss/Lee","schoolDistrict":"Baldwyn School District"},{"teamSlug":"Bay","schoolAffiliation":"MHSAA","schoolTown":"Bay St. Louis","schoolCounty":"Hancock","schoolDistrict":"Bay St. Louis-Waveland School District"},{"teamSlug":"Bayouacademy","schoolAffiliation":"MAIS","schoolTown":"Cleveland","schoolCounty":"Bolivar"}]